{
	"Andorra": [{
		"name": "Hotel Catalunya",
		"city": "Pas de la Casa"
	}],
	"Angola": [{
		"name": "Restaurante Madeirense",
		"city": "Luanda"
	}],
	"Belgium": [{
			"name": "Café Portugal",
			"city": "Bruxelas"
		},
		{
			"name": "O Cambalhotas",
			"city": "Bruxelas"
		}
	],
	"Brazil": [{
			"name": "Espeto Brasileiro",
			"city": "Rio de Janeiro"
		},
		{
			"name": "Cantinho Português",
			"city": "São Paulo"
		}
	],
	"Canada": [{
			"name": "Portuguese Cultural Centre of Kingston",
			"city": "Kingston"
		},
		{
			"name": "Portuguese Club Of Vancouver (PCOV)",
			"city": "Vancouver"
		},
		{
			"name": "Serra Coffee Bar & Billiards",
			"city": "Vancouver"
		}
	],
	"Czech": [{
		"name": "Café Oliveira",
		"city": "Praga"
	}],
	"France": [{
		"name": "Casa do Benfica de Paris",
		"city": "Paris"
	}],
	"Germany": [{
			"name": "Café Lisboa",
			"city": "Berlim"
		},
		{
			"name": "Frango Português",
			"city": "Düsseldorf"
		},
		{
			"name": "Tasquinha da Jacinta",
			"city": "Frankfurt"
		},
		{
			"name": "Gaststätte Benfica",
			"city": "Hamburgo"
		},
		{
			"name": "Restaurante Portugal",
			"city": "Munique"
		},
		{
			"name": "Associação Recreativa Portuguesa Sindelfingen",
			"city": "Sindelfingen"
		}
	],
	"Hungary": [{
		"name": "John Bull Sport Pub & Restaurant",
		"city": "Budapeste"
	}],
	"Ireland": [{
			"name": "Murray's Pub",
			"city": "Dublin"
		},
		{
			"name": "The Living Room",
			"city": "Dublin"
		}
	],
	"Lithuania": [{
			"name": "rePUBlic No.1",
			"city": "Kaunas"
		},
		{
			"name": "rePUBlic No. 4",
			"city": "Vilnius"
		},
		{
			"name": "Crazy Bull",
			"city": "Vilnius"
		}
	],
	"Mozambique": [{
		"name": "Mundos",
		"city": "Maputo"
	}],
	"Netherlands": [{
			"name": "Old Sailor Pub",
			"city": "Amesterdão"
		},
		{
			"name": "gdr Os Lusitanos",
			"city": "Amesterdão"
		},
		{
			"name": "Satellite Sportscafé",
			"city": "Amesterdão"
		}
	],
	"Poland": [{
		"name": "Champion's Sports Bar",
		"city": "Varsóvia"
	}],
	"Portugal": [{
			"name": "CRCA - Centro Recreativo e Cultural de Assentiz",
			"city": "Assentiz"
		},
		{
			"name": "The George",
			"city": "Lisboa"
		}
	],
	"Romania": [{
		"name": "Mojo Music Club",
		"city": "Bucareste"
	}],
	"Slovenia": [{
		"name": "Cutty Sark Pub",
		"city": "Ljubliana"
	}],
	"Spain": [{
			"name": "Bistro 42",
			"city": "Barcelona"
		},
		{
			"name": "Docemasuno Sports Bar",
			"city": "Barcelona"
		},
		{
			"name": "La Burnessa",
			"city": "Barcelona"
		},
		{
			"name": "Dow Jones",
			"city": "Barcelona"
		},
		{
			"name": "Maria La Portuguesa",
			"city": "Madrid"
		},
		{
			"name": "Frangus",
			"city": "Madrid"
		},
		{
			"name": "Nino Ferreira",
			"city": "Madrid"
		},
		{
			"name": "A Novena Porta",
			"city": "Santiago de Compostela"
		}
	],
	"Switzerland": [{
			"name": "Lausanne Sport Benfica",
			"city": "Lausanne"
		},
		{
			"name": "Restaurante Bem me Quer",
			"city": "Saint Gallen"
		}
	],
	"United Kingdom": [{
			"name": "Brig O' Tay",
			"city": "Dundee"
		},
		{
			"name": "The Tron",
			"city": "Edimburgo"
		},
		{
			"name": "Cafe Porto",
			"city": "Liverpool"
		},
		{
			"name": "O Moinho",
			"city": "Londres"
		},
		{
			"name": "Bar & Co",
			"city": "Londres"
		},
		{
			"name": "O Tino",
			"city": "Londres"
		},
		{
			"name": "Cafe Tejo",
			"city": "Londres"
		},
		{
			"name": "Casa do Benfica de Londres",
			"city": "Londres"
		},
		{
			"name": "Sabor Latino",
			"city": "Londres"
		},
		{
			"name": "A Toca",
			"city": "Londres"
		},
		{
			"name": "Walkabout",
			"city": "Manchester"
		},
		{
			"name": "Cafe Football",
			"city": "Manchester"
		},
		{
			"name": "A Tasca",
			"city": "Peterborough"
		}
	],
	"United States": [{
			"name": "Casa Benfica Cambridge",
			"city": "Boston"
		},
		{
			"name": "Legends",
			"city": "Nova Iorque"
		},
		{
			"name": "Hooters",
			"city": "Nova Iorque"
		}
	]
}
